pathtyped/__init__.py
pathtyped/lib.py
pathtyped/loaders.py
pathtyped/middlewares.py
pathtyped/py.typed
pathtyped-0.1.4.dist-info/LICENSE
pathtyped-0.1.4.dist-info/METADATA
pathtyped-0.1.4.dist-info/WHEEL
pathtyped-0.1.4.dist-info/top_level.txt
pathtyped-0.1.4.dist-info/RECORD
