Metadata-Version: 2.1
Name: pathtyped
Version: 0.1.4
Summary: Create static path checking and type checking for your Python code
Author: nopeless
License: MIT License
Project-URL: Homepage, https://github.com/nopeless/python-typesafe-resource-management
Project-URL: Bug Tracker, https://github.com/nopeless/python-typesafe-resource-management/issues
Keywords: path,file,type
Classifier: Programming Language :: Python :: 3
Classifier: License :: OSI Approved :: MIT License
Classifier: Operating System :: OS Independent
Requires-Python: >=3.10
License-File: LICENSE
Provides-Extra: dev
Requires-Dist: black ; extra == 'dev'
Requires-Dist: pytest ; extra == 'dev'
